odoo/addons/connector_importer/README.rst
odoo/addons/connector_importer/__init__.py
odoo/addons/connector_importer/__manifest__.py
odoo/addons/connector_importer/events.py
odoo/addons/connector_importer/log.py
odoo/addons/connector_importer/menuitems.xml
odoo/addons/connector_importer/components/__init__.py
odoo/addons/connector_importer/components/automapper.py
odoo/addons/connector_importer/components/base.py
odoo/addons/connector_importer/components/dynamicmapper.py
odoo/addons/connector_importer/components/importer.py
odoo/addons/connector_importer/components/importer_csv_std.py
odoo/addons/connector_importer/components/listeners.py
odoo/addons/connector_importer/components/mapper.py
odoo/addons/connector_importer/components/odoorecord.py
odoo/addons/connector_importer/components/odoorecord_csv_std.py
odoo/addons/connector_importer/components/tracker.py
odoo/addons/connector_importer/controllers/__init__.py
odoo/addons/connector_importer/controllers/main.py
odoo/addons/connector_importer/data/ir_cron.xml
odoo/addons/connector_importer/data/queue_job_function_data.xml
odoo/addons/connector_importer/i18n/connector_importer.pot
odoo/addons/connector_importer/i18n/it.po
odoo/addons/connector_importer/models/__init__.py
odoo/addons/connector_importer/models/backend.py
odoo/addons/connector_importer/models/cron_mixin.py
odoo/addons/connector_importer/models/import_type.py
odoo/addons/connector_importer/models/job_mixin.py
odoo/addons/connector_importer/models/record.py
odoo/addons/connector_importer/models/recordset.py
odoo/addons/connector_importer/models/reporter.py
odoo/addons/connector_importer/models/sources/__init__.py
odoo/addons/connector_importer/models/sources/source_consumer_mixin.py
odoo/addons/connector_importer/models/sources/source_csv.py
odoo/addons/connector_importer/models/sources/source_mixin.py
odoo/addons/connector_importer/readme/CONFIGURE.md
odoo/addons/connector_importer/readme/CONTRIBUTORS.md
odoo/addons/connector_importer/readme/CREDITS.md
odoo_addon_connector_importer-18.0.1.2.0.dist-info/METADATA
odoo_addon_connector_importer-18.0.1.2.0.dist-info/WHEEL
odoo_addon_connector_importer-18.0.1.2.0.dist-info/top_level.txt
odoo_addon_connector_importer-18.0.1.2.0.dist-info/RECORD
