Metadata-Version: 2.1
Name: odoo-addon-connector_importer
Version: 18.0.1.2.0
Requires-Python: >=3.10
Requires-Dist: chardet
Requires-Dist: odoo-addon-connector==18.0.*
Requires-Dist: odoo-addon-queue_job==18.0.*
Requires-Dist: odoo==18.0.*
Requires-Dist: pytz
Requires-Dist: pyyaml
Summary: This module takes care of import sessions.
Home-page: https://github.com/OCA/connector-interfaces
License: AGPL-3
Author: Camptocamp, Odoo Community Association (OCA)
Author-email: support@odoo-community.org
Classifier: Programming Language :: Python
Classifier: Framework :: Odoo
Classifier: Framework :: Odoo :: 18.0
Classifier: License :: OSI Approved :: GNU Affero General Public License v3
